cssselectorbuilder-0.4.3.dist-info/METADATA
cssselectorbuilder-0.4.3.dist-info/WHEEL
cssselectorbuilder-0.4.3.dist-info/licenses/LICENSE
cssselectorbuilder/__init__.py
cssselectorbuilder-0.4.3.dist-info/RECORD
