Metadata-Version: 2.1
Name: CssSelectorBuilder
Version: 0.4.3
Summary: Package that helps you to build compley css selectors
Author-Email: j.ernst <johannes@ernstcloud.de>
License: MIT
Requires-Python: >=3.9
Provides-Extra: dev
Requires-Dist: build>=1.0.3; extra == "dev"
Requires-Dist: twine>=4.0.2; extra == "dev"
Requires-Dist: pytest>=7.4.2; extra == "dev"
